corva_data_dataset/__init__.py
corva_data_dataset/api_client.py
corva_data_dataset/api_response.py
corva_data_dataset/configuration.py
corva_data_dataset/exceptions.py
corva_data_dataset/py.typed
corva_data_dataset/rest.py
corva_data_dataset/api/__init__.py
corva_data_dataset/api/corva_dataset_api.py
corva_data_dataset/models/__init__.py
corva_data_dataset/models/corva_dataset.py
corva_data_dataset/models/http_validation_error.py
corva_data_dataset-1.0.1.dist-info/METADATA
corva_data_dataset-1.0.1.dist-info/WHEEL
corva_data_dataset-1.0.1.dist-info/top_level.txt
corva_data_dataset-1.0.1.dist-info/RECORD
